<SpecTranslations>

  <Axe.label>sekera</Axe.label> <!-- <En>axe</En> -->
  <Axe.description>Silná, ale únavná. Použití stojí výdrž.</Axe.description> <!-- <En>Powerful but tiring. Costs stamina to use.</En> -->

  <Bow.label>luk</Bow.label> <!-- <En>bow</En> -->
  <Bow.description>Dobrá zbraň pro boj na dálku.</Bow.description> <!-- <En>A good weapon for long-range combat.</En> -->

  <ElectricSword.label>elektrický meč</ElectricSword.label> <!-- <En>electric sword</En> -->
  <ElectricSword.description>Tento meč zraní i nepřátele na sousedních polích.</ElectricSword.description> <!-- <En>This sword will also harm the adjacent enemies.</En> -->

  <Flamethrower.label>plamenomet</Flamethrower.label> <!-- <En>flamethrower</En> -->
  <Flamethrower.description>Dobrá zbraň ke spálení všeho.</Flamethrower.description> <!-- <En>A good weapon for burning everything down.</En> -->

  <FlintlockPistol.label>křesadlová pistole</FlintlockPistol.label> <!-- <En>flintlock pistol</En> -->
  <FlintlockPistol.description>Silná, ale pomalá zbraň.</FlintlockPistol.description> <!-- <En>A powerful but slow weapon.</En> -->

  <HeavyBow.label>těžký luk</HeavyBow.label> <!-- <En>heavy bow</En> -->
  <HeavyBow.description>Těžší verze standardního luku. Smrtelnější, ale také se s ním hůře zachází.</HeavyBow.description> <!-- <En>A heavier version of the standard bow. More deadly, but also more difficult to handle.</En> -->

  <Mace.label>palcát</Mace.label> <!-- <En>mace</En> -->
  <Mace.description>Spolehlivý a předvídatelný.</Mace.description> <!-- <En>Reliable and predictable.</En> -->

  <Pike.label>píka</Pike.label> <!-- <En>pike</En> -->
  <Pike.description>Umožňuje útočit na nepřátele z dálky. Použití vyžaduje hodně výdrže.</Pike.description> <!-- <En>Lets you attack enemies from a distance. Requires a lot of stamina to use.</En> -->

  <Sword.label_2>meč</Sword.label_2> <!-- <En>sword</En> -->
  <Sword.description_2>Obyčejný meč z obyčejného dungeonu. Čím hlouběji v dungeonu jsi, tím silnější zbraně najdeš.</Sword.description_2> <!-- <En>An ordinary sword from an ordinary dungeon. The lower you are in the dungeon, the stronger weapons you'll find.</En> -->

</SpecTranslations>