<SpecTranslations>

  <Main1.label>Caverna del Amanecer</Main1.label> <!-- <En>Cavern of Dawn</En> -->

  <Main2.label>Campos de Juego</Main2.label> <!-- <En>Playgrounds</En> -->

  <Main3.label>Encrucijada</Main3.label> <!-- <En>Crossroads</En> -->

  <Main4.label>Laberinto</Main4.label> <!-- <En>Labyrinth</En> -->

  <Main5.label>Cripta del Reflejo</Main5.label> <!-- <En>Crypt of Reflection</En> -->

  <Main6.label>Bóveda de la Sabiduría</Main6.label> <!-- <En>Vault of Wisdom</En> -->

  <Main7.label>Guarida de la Soledad</Main7.label> <!-- <En>Den of Solitude</En> -->

  <Main8.label>Cuevas del Crepúsculo</Main8.label> <!-- <En>Twilight Caves</En> -->

  <Main9.label>Cuevas Interminables</Main9.label> <!-- <En>Endless Caves</En> -->

</SpecTranslations>
