<SpecTranslations>

  <Archer.label>łucznik</Archer.label> <!-- <En>archer</En> -->
  <Archer.description>Preferuje walkę na dystans i trzyma się z daleka, chyba że zostanie osaczony.</Archer.description> <!-- <En>Prefers ranged combat and keeps distance unless cornered.</En> -->

  <Dragon.label>smok</Dragon.label> <!-- <En>dragon</En> -->
  <Dragon.description>Wściekły, potężny smok w całej okazałości.</Dragon.description> <!-- <En>An angry, powerful dragon in all its glory.</En> -->

  <Exploder.label>wybuchacz</Exploder.label> <!-- <En>exploder</En> -->
  <Exploder.description>Wybucha, gdy zginie.</Exploder.description> <!-- <En>Explodes when killed.</En> -->

  <Mimic.label>mimik</Mimic.label> <!-- <En>mimic</En> -->
  <Mimic.description>Niespodzianka!</Mimic.description> <!-- <En>Surprise!</En> -->

  <Mole.label>kret</Mole.label> <!-- <En>mole</En> -->
  <Mole.description>Lubi chować się tu i tam.</Mole.description> <!-- <En>Likes to hide here and there.</En> -->

  <Mummy.label>mumia</Mummy.label> <!-- <En>mummy</En> -->
  <Mummy.description>Powolna, ale silna.</Mummy.description> <!-- <En>Slow but strong.</En> -->

  <Mutant.label>mutant</Mutant.label> <!-- <En>mutant</En> -->
  <Mutant.description>Obrzydliwy potwór. Ma szansę wywołać u ciebie panikę po trafieniu.</Mutant.description> <!-- <En>A hideous monster. Has a chance to make you panic when you're hit.</En> -->

  <Nimlet.label>nimlet</Nimlet.label> <!-- <En>nimlet</En> -->
  <Nimlet.description>Niezbyt silny, ale dość irytujący. Nie podchodzi pierwszy.</Nimlet.description> <!-- <En>Not very strong, but quite annoying. Doesn't approach first.</En> -->

  <Ninja.label>ninja</Ninja.label> <!-- <En>ninja</En> -->
  <Ninja.description>Szybki i zabójczy. Wycofuje się po ataku, by uniknąć trafienia.</Ninja.description> <!-- <En>Fast and deadly. Backs off after attacking you to avoid getting hit.</En> -->

  <Phantom.label>zjawa</Phantom.label> <!-- <En>phantom</En> -->
  <Phantom.description>Niepokojąca, lewitująca bestia.</Phantom.description> <!-- <En>A disturbing, levitating beast.</En> -->

  <Rammok.label>rammok</Rammok.label> <!-- <En>rammok</En> -->
  <Rammok.description>Duży i wściekły potwór. Czasami odpycha cię po trafieniu.</Rammok.description> <!-- <En>A big and angry monster. He'll sometimes push you when you're hit.</En> -->

  <Rat.label>szczur</Rat.label> <!-- <En>rat</En> -->
  <Rat.description>Uciążliwy szczur. Szczury mogą czasami pojawiać się za twoimi plecami.</Rat.description> <!-- <En>A pesky rat. Rats can sometimes spawn behind your back.</En> -->

  <Rogue.label_2>łotr</Rogue.label_2> <!-- <En>rogue</En> -->
  <Rogue.description_2>Atakuje, a potem ucieka.</Rogue.description_2> <!-- <En>Attacks and then runs away.</En> -->

  <Skeleton.label>szkielet</Skeleton.label> <!-- <En>skeleton</En> -->
  <Skeleton.description>Typowy mieszkaniec tego lochu.</Skeleton.description> <!-- <En>A typical inhabitant of this dungeon.</En> -->

  <Slime.label>szlam</Slime.label> <!-- <En>slime</En> -->
  <Slime.description>Wściekła kupa zielonego szlamu, która po zabiciu rozpada się na mniejsze kawałki.</Slime.description> <!-- <En>An angry blob of green slime which will split into smaller pieces when killed.</En> -->

  <Sludgen.label>szlamowiec</Sludgen.label> <!-- <En>sludgen</En> -->
  <Sludgen.description>Nie pachnie ładnie.</Sludgen.description> <!-- <En>Doesn't smell nice.</En> -->

  <SmallSlime.label>mały szlam</SmallSlime.label> <!-- <En>small slime</En> -->
  <SmallSlime.description>Mniejsza i mniej wściekła wersja dużej kupy szlamu.</SmallSlime.description> <!-- <En>A smaller and less angry version of the big blob.</En> -->

  <Spider.label>pająk</Spider.label> <!-- <En>spider</En> -->
  <Spider.description>Chowa się w różnych miejscach. Może zatruć swoją ofiarę. Nienawidzi wszystkich.</Spider.description> <!-- <En>Hides in various places. Can poison its prey. Hates everyone.</En> -->

  <Summoner.label>przywoływacz</Summoner.label> <!-- <En>summoner</En> -->
  <Summoner.description>Przywołuje zabójcze stworzenia.</Summoner.description> <!-- <En>Summons deadly creatures.</En> -->

  <Tangler.label>plątacz</Tangler.label> <!-- <En>tangler</En> -->
  <Tangler.description>Dość silny, ale niezdarny. Ma szansę cię oplątać, gdy zostaniesz trafiony.</Tangler.description> <!-- <En>Quite strong, but clumsy. There's a chance he'll entangle you when you're hit.</En> -->

  <Trickster.label>szachraj</Trickster.label> <!-- <En>trickster</En> -->
  <Trickster.description>Ma kilka sztuczek w rękawie. Każdy szachraj posiada losowe zaklęcie.</Trickster.description> <!-- <En>Keeps a few tricks up his sleeve. Every trickster has a random spell.</En> -->

  <Wasp.label>osa</Wasp.label> <!-- <En>wasp</En> -->
  <Wasp.description>Łatwa do zabicia, ale wciąż niebezpieczna. Osy zazwyczaj pochodzą z gniazd os.</Wasp.description> <!-- <En>Easy to kill but still dangerous. Wasps usually come from wasp nests.</En> -->

  <Wizard.label>czarodziej</Wizard.label> <!-- <En>wizard</En> -->
  <Wizard.description>Zadaje magiczne obrażenia na odległość.</Wizard.description> <!-- <En>Deals magic damage from a distance.</En> -->

</SpecTranslations>