<SpecTranslations>

  <Darkness.label_2>sötétség</Darkness.label_2> <!-- <En>darkness</En> -->
  <Darkness.description>Minden elsötétült. Mindenki látótávolsága egy mezővel csökkent, megjelent két szellem, és minden fáklya kialudt.</Darkness.description> <!-- <En>Everything's gone dark. Vision is reduced by one cell for everyone, two ghosts have appeared, and all torches are out.</En> -->

  <Earthquake.label_2>földrengés</Earthquake.label_2> <!-- <En>earthquake</En> -->
  <Earthquake.description>A föld remeg és sziklák hullanak a mennyezetről.</Earthquake.description> <!-- <En>The ground is shaking and rocks are falling from the ceiling.</En> -->

  <PoisonWave.label_2>méreghullám</PoisonWave.label_2> <!-- <En>poison wave</En> -->
  <PoisonWave.description>Méreghullám söpör végig a kazamatán. Véletlenszerű helyeken méregfelhők jelennek meg.</PoisonWave.description> <!-- <En>A wave of poison is sweeping across the dungeon. Poison clouds will appear in random places.</En> -->

  <Vulnerability.label_2>sebezhetőség</Vulnerability.label_2> <!-- <En>vulnerability</En> -->
  <Vulnerability.description>Mindenki sebezhetőnek érzi magát és kétszer annyi fizikai sebzést szenved el.</Vulnerability.description> <!-- <En>Everyone feels vulnerable and receives twice as much physical damage.</En> -->

  <WaspSwarm.label_2>darázsraj</WaspSwarm.label_2> <!-- <En>wasp swarm</En> -->
  <WaspSwarm.description>Egy darázsraj közeledik.</WaspSwarm.description> <!-- <En>A swarm of wasps is incoming.</En> -->

</SpecTranslations>