<SpecTranslations>

  <Bomb_Black.label>قنبلة سوداء</Bomb_Black.label> <!-- <En>black bomb</En> -->
  <Bomb_Black.description>نوع من القنابل.</Bomb_Black.description> <!-- <En>Some kind of a bomb.</En> -->

  <Bomb_Blue.label>قنبلة زرقاء</Bomb_Blue.label> <!-- <En>blue bomb</En> -->
  <Bomb_Blue.description>نوع من القنابل.</Bomb_Blue.description> <!-- <En>Some kind of a bomb.</En> -->

  <Bomb_Green.label>قنبلة خضراء</Bomb_Green.label> <!-- <En>green bomb</En> -->
  <Bomb_Green.description>نوع من القنابل.</Bomb_Green.description> <!-- <En>Some kind of a bomb.</En> -->

  <Bomb_Red.label>قنبلة حمراء</Bomb_Red.label> <!-- <En>red bomb</En> -->
  <Bomb_Red.description>نوع من القنابل.</Bomb_Red.description> <!-- <En>Some kind of a bomb.</En> -->

  <Bomb_White.label>قنبلة بيضاء</Bomb_White.label> <!-- <En>white bomb</En> -->
  <Bomb_White.description>نوع من القنابل.</Bomb_White.description> <!-- <En>Some kind of a bomb.</En> -->

  <Bomb_Yellow.label>قنبلة صفراء</Bomb_Yellow.label> <!-- <En>yellow bomb</En> -->
  <Bomb_Yellow.description>نوع من القنابل.</Bomb_Yellow.description> <!-- <En>Some kind of a bomb.</En> -->

</SpecTranslations>