<SpecTranslations>

  <Potion_Black.label>černý lektvar</Potion_Black.label> <!-- <En>black potion</En> -->
  <Potion_Black.description>Buď ho vypij, nebo ho hoď na někoho jiného.</Potion_Black.description> <!-- <En>Either drink it or throw it at someone else.</En> -->

  <Potion_Blue.label>modrý lektvar</Potion_Blue.label> <!-- <En>blue potion</En> -->
  <Potion_Blue.description>Buď ho vypij, nebo ho hoď na někoho jiného.</Potion_Blue.description> <!-- <En>Either drink it or throw it at someone else.</En> -->

  <Potion_Brown.label>hnědý lektvar</Potion_Brown.label> <!-- <En>brown potion</En> -->
  <Potion_Brown.description>Buď ho vypij, nebo ho hoď na někoho jiného.</Potion_Brown.description> <!-- <En>Either drink it or throw it at someone else.</En> -->

  <Potion_Cyan.label>azurový lektvar</Potion_Cyan.label> <!-- <En>cyan potion</En> -->
  <Potion_Cyan.description>Buď ho vypij, nebo ho hoď na někoho jiného.</Potion_Cyan.description> <!-- <En>Either drink it or throw it at someone else.</En> -->

  <Potion_Green.label>zelený lektvar</Potion_Green.label> <!-- <En>green potion</En> -->
  <Potion_Green.description>Buď ho vypij, nebo ho hoď na někoho jiného.</Potion_Green.description> <!-- <En>Either drink it or throw it at someone else.</En> -->

  <Potion_Orange.label>oranžový lektvar</Potion_Orange.label> <!-- <En>orange potion</En> -->
  <Potion_Orange.description>Buď ho vypij, nebo ho hoď na někoho jiného.</Potion_Orange.description> <!-- <En>Either drink it or throw it at someone else.</En> -->

  <Potion_Purple.label>fialový lektvar</Potion_Purple.label> <!-- <En>purple potion</En> -->
  <Potion_Purple.description>Buď ho vypij, nebo ho hoď na někoho jiného.</Potion_Purple.description> <!-- <En>Either drink it or throw it at someone else.</En> -->

  <Potion_Red.label>červený lektvar</Potion_Red.label> <!-- <En>red potion</En> -->
  <Potion_Red.description>Buď ho vypij, nebo ho hoď na někoho jiného.</Potion_Red.description> <!-- <En>Either drink it or throw it at someone else.</En> -->

  <Potion_Violet.label>purpurový lektvar</Potion_Violet.label> <!-- <En>violet potion</En> -->
  <Potion_Violet.description>Buď ho vypij, nebo ho hoď na někoho jiného.</Potion_Violet.description> <!-- <En>Either drink it or throw it at someone else.</En> -->

  <Potion_White.label>bílý lektvar</Potion_White.label> <!-- <En>white potion</En> -->
  <Potion_White.description>Buď ho vypij, nebo ho hoď na někoho jiného.</Potion_White.description> <!-- <En>Either drink it or throw it at someone else.</En> -->

  <Potion_Yellow.label>žlutý lektvar</Potion_Yellow.label> <!-- <En>yellow potion</En> -->
  <Potion_Yellow.description>Buď ho vypij, nebo ho hoď na někoho jiného.</Potion_Yellow.description> <!-- <En>Either drink it or throw it at someone else.</En> -->

</SpecTranslations>