<SpecTranslations>

  <Codex.label>kodex</Codex.label> <!-- <En>codex</En> -->
  <Codex.description>Se alla föremål och varelser du någonsin har sett.</Codex.description> <!-- <En>View all items and creatures you have ever seen.</En> -->

  <DungeonMap.label>grottkarta</DungeonMap.label> <!-- <En>dungeon map</En> -->
  <DungeonMap.description>Se kartan över denna grotta.</DungeonMap.description> <!-- <En>View the map of this dungeon.</En> -->

  <Factions.label>fraktioner</Factions.label> <!-- <En>factions</En> -->
  <Factions.description>Se alla fraktioner i denna grotta.</Factions.description> <!-- <En>View all factions in this dungeon.</En> -->

  <Inventory.label_2>inventarie</Inventory.label_2> <!-- <En>inventory</En> -->
  <Inventory.description>Se de föremål du har i din inventarie.</Inventory.description> <!-- <En>View items you have in your inventory.</En> -->

  <Quests.label>uppdrag</Quests.label> <!-- <En>quests</En> -->
  <Quests.description>Se dina uppdrag.</Quests.description> <!-- <En>View your quests.</En> -->

  <Skills.label>färdigheter</Skills.label> <!-- <En>skills</En> -->
  <Skills.description>Se ditt färdighetsträd. Spendera färdighetspoäng för att lära dig nya färdigheter.</Skills.description> <!-- <En>View your skill tree. Spend skill points to learn new skills.</En> -->

</SpecTranslations>