<SpecTranslations>

  <DigUpGrave.label>scava la tomba</DigUpGrave.label> <!-- <En>dig up grave</En> -->
  <DigUpGrave.description>Cerca un tesoro.</DigUpGrave.description> <!-- <En>Search for a treasure.</En> -->

  <Search.label>cerca</Search.label> <!-- <En>search</En> -->
  <Search.description>Cerca tesori nascosti.</Search.description> <!-- <En>Search for hidden treasures.</En> -->

  <UnknownMechanism.label>meccanismo sconosciuto</UnknownMechanism.label> <!-- <En>unknown mechanism</En> -->
  <UnknownMechanism.description>Qualcosa accadrà... o forse no.</UnknownMechanism.description> <!-- <En>Something will happen... or not.</En> -->

</SpecTranslations>