<SpecTranslations>

  <Easy.label>nhẹ</Easy.label> <!-- <En>mild</En> -->
  <Easy.description>Một trải nghiệm đầy thử thách nhưng nhẹ nhàng hơn một chút. Đây là độ khó được đề xuất cho những người chơi mới làm quen với thể loại khám phá hầm ngục.</Easy.description> <!-- <En>A challenging but a bit milder experience. This is the recommended difficulty for new dungeon crawler players.</En> -->

  <Hard.label>khắc nghiệt</Hard.label> <!-- <En>extreme</En> -->
  <Hard.description>Độ khó cao nhất dành cho những người chơi dày dạn kinh nghiệm. Trò chơi thử thách hơn, nhưng phần thưởng cũng hậu hĩnh hơn.</Hard.description> <!-- <En>The highest difficulty for experienced players. The game is more challenging, but also more rewarding.</En> -->

  <Normal.label>gai góc</Normal.label> <!-- <En>rough</En> -->
  <Normal.description>Đây là trải nghiệm nguyên bản của trò chơi. Hãy chuẩn bị tinh thần để chết thường xuyên, kể cả khi chỉ chạm trán một lần nếu bạn không may mắn.</Normal.description> <!-- <En>This is how the game was meant to be played. Be prepared to die often, even from a single encounter if you're unlucky.</En> -->

</SpecTranslations>